LICENSE
MANIFEST.in
README.rst
setup.py
dpcanvas/__init__.py
dpcanvas/apps.py
dpcanvas/urls.py
dpcanvas.egg-info/PKG-INFO
dpcanvas.egg-info/SOURCES.txt
dpcanvas.egg-info/dependency_links.txt
dpcanvas.egg-info/requires.txt
dpcanvas.egg-info/top_level.txt
dpcanvas/admin/Canvas.py
dpcanvas/admin/__init__.py
dpcanvas/managers/CanvasManager.py
dpcanvas/managers/__init__.py
dpcanvas/migrations/0001_initial.py
dpcanvas/migrations/0002_canvas_user.py
dpcanvas/migrations/0003_auto_20170523_1339.py
dpcanvas/migrations/0004_auto_20170524_1008.py
dpcanvas/migrations/0005_auto_20170524_1212.py
dpcanvas/migrations/__init__.py
dpcanvas/model_bases/AbstractBaseCanvas.py
dpcanvas/model_bases/__init__.py
dpcanvas/models/Canvas.py
dpcanvas/models/__init__.py
dpcanvas/serializers/__init__.py
dpcanvas/serializers/canvas_lc.py
dpcanvas/serializers/canvas_rud.py
dpcanvas/signals/__init__.py
dpcanvas/signals/handlers.py
dpcanvas/views/__init__.py
dpcanvas/views/canvas_lc.py
dpcanvas/views/canvas_rud.py